drive_in/__about__.py
drive_in/__init__.py
drive_in/_constants.py
drive_in/core.py
drive_in/helpers.py
drive_in/py.typed
drive_in/types.py
drive_in-0.1.5.dist-info/METADATA
drive_in-0.1.5.dist-info/WHEEL
drive_in-0.1.5.dist-info/licenses/LICENSE
drive_in-0.1.5.dist-info/licenses/LICENSE.txt
drive_in-0.1.5.dist-info/RECORD
