Metadata-Version: 2.1
Name: drive-in
Version: 0.1.5
Summary: Minimalistic Google Drive Library for Python
Project-URL: Documentation, https://github.com/robinvandernoord/drive-in#readme
Project-URL: Issues, https://github.com/robinvandernoord/drive-in/issues
Project-URL: Source, https://github.com/robinvandernoord/drive-in
Author-email: Robin van der Noord <robinvandernoord@gmail.com>
License-Expression: MIT
License-File: LICENSE
License-File: LICENSE.txt
Classifier: Development Status :: 4 - Beta
Classifier: Programming Language :: Python
Classifier: Programming Language :: Python :: 3.10
Classifier: Programming Language :: Python :: 3.11
Classifier: Programming Language :: Python :: 3.12
Classifier: Programming Language :: Python :: Implementation :: CPython
Classifier: Programming Language :: Python :: Implementation :: PyPy
Requires-Python: >=3.10
Requires-Dist: configuraptor>=1.20.0
Requires-Dist: tqdm
Requires-Dist: yayarl
Provides-Extra: dev
Requires-Dist: hatch; extra == 'dev'
Requires-Dist: su6[all]; extra == 'dev'
Requires-Dist: types-requests; extra == 'dev'
